ds_python/__init__.py
ds_python/__main__.py
ds_python/main.py
ds_python/ui.py
ds_python/utils.py
ds_python-0.1.4.dist-info/METADATA
ds_python-0.1.4.dist-info/WHEEL
ds_python-0.1.4.dist-info/entry_points.txt
ds_python-0.1.4.dist-info/licenses/LICENSE
ds_python-0.1.4.dist-info/RECORD
