Metadata-Version: 2.4
Name: ds-python
Version: 0.1.4
Summary: Add your description here
Project-URL: repository, https://github.com/Gpocas/ds-python
Project-URL: Bug Tracker, https://github.com/Gpocas/ds-python/issues
Author-email: Gpocas <gpocas01@gmail.com>
License-File: LICENSE
Classifier: Development Status :: 5 - Production/Stable
Classifier: Natural Language :: Portuguese (Brazilian)
Classifier: Programming Language :: Python :: 3.12
Classifier: Topic :: Software Development :: Build Tools
Classifier: Topic :: Software Development :: Libraries :: Python Modules
Requires-Python: >=3.12
Requires-Dist: dashing>=0.1.0
Requires-Dist: rich>=13.9.4
